loadtime/__init__.py
loadtime/load_time.py
loadtime-1.0.6.dist-info/LICENSE
loadtime-1.0.6.dist-info/METADATA
loadtime-1.0.6.dist-info/WHEEL
loadtime-1.0.6.dist-info/top_level.txt
loadtime-1.0.6.dist-info/RECORD
