Metadata-Version: 2.1
Name: loadtime
Version: 1.0.6
Summary: Package to display a progress bar for long processes with uncertain end times
Home-page: https://github.com/qualiteg/LoadTime
Author: Qualiteg Inc.
Author-email: qualiteger@qualiteg.com
Classifier: Development Status :: 4 - Beta
Classifier: Intended Audience :: Developers
Classifier: License :: OSI Approved :: Apache Software License
Classifier: Programming Language :: Python :: 3.8
Classifier: Programming Language :: Python :: 3.9
Classifier: Programming Language :: Python :: 3.10
Requires-Python: >=3.8
License-File: LICENSE
